rust_strings-0.6.0.dist-info/METADATA
rust_strings-0.6.0.dist-info/WHEEL
rust_strings-0.6.0.dist-info/license_files/LICENSE.txt
rust_strings/__init__.py
rust_strings/__init__.pyi
rust_strings/py.typed
rust_strings/rust_strings.cpython-311-powerpc64-linux-gnu.so
rust_strings-0.6.0.dist-info/RECORD
