Metadata-Version: 2.1
Name: rust-strings
Version: 0.6.0
Classifier: Topic :: Software Development
Classifier: Programming Language :: Python :: 3.7
Classifier: Programming Language :: Python :: 3.8
Classifier: Programming Language :: Python :: 3.9
Classifier: Programming Language :: Python :: 3.10
Classifier: Programming Language :: Python :: 3.11
Classifier: Programming Language :: Python :: 3.12
Classifier: Programming Language :: Python :: Implementation :: CPython
Classifier: Programming Language :: Rust
License-File: LICENSE.txt
Summary: Extract strings from binary data
Keywords: strings
Home-Page: https://github.com/iddohau/rust-strings
Author: iddohau@gmail.com
Author-email: Iddo Hauschner <iddohau@gmail.com>
Maintainer-email: Iddo Hauschner <iddohau@gmail.com>
License: MIT
Requires-Python: >=3.7
Project-URL: Source Code, https://github.com/iddohau/rust-strings
